adgmaker/__init__.py
adgmaker/adgmaker.py
adgmaker/base_xml.tpl
adgmaker/instrument_xml.tpl
adgmaker-0.1.3.dist-info/DESCRIPTION.rst
adgmaker-0.1.3.dist-info/entry_points.txt
adgmaker-0.1.3.dist-info/METADATA
adgmaker-0.1.3.dist-info/metadata.json
adgmaker-0.1.3.dist-info/RECORD
adgmaker-0.1.3.dist-info/top_level.txt
adgmaker-0.1.3.dist-info/WHEEL
