Metadata-Version: 2.0
Name: adgmaker
Version: 0.1.3
Summary: Create Free Ableton Live Instruments from Philharmonic Samples
Home-page: https://github.com/Miserlou/ADGMaker
Author: Rich Jones
Author-email: rich@openwatch.net
License: MIT License
Platform: UNKNOWN
Classifier: Environment :: Console
Classifier: License :: OSI Approved :: Apache Software License
Classifier: Operating System :: OS Independent
Classifier: Programming Language :: Python
Classifier: Programming Language :: Python :: 2.7
Classifier: Topic :: Internet :: WWW/HTTP
Classifier: Topic :: Internet :: WWW/HTTP :: Dynamic Content
Requires-Dist: Jinja2 (==2.8)
Requires-Dist: MarkupSafe (==0.23)
Requires-Dist: requests (==2.10.0)
Requires-Dist: wheel (==0.24.0)
